industryguesser
