Metadata-Version: 2.1
Name: IndustryGuesser
Version: 0.1.2
Summary: Guess the company industry based on the company name
Home-page: https://pypi.org/project/IndustryGuesser/
Author: yang zhengzhi
Author-email: yangzhengzhi.roy@gmail.com
License: UNKNOWN
Download-URL: https://github.com/yangzhengzhiroy/IndustryGuesser/archive/v0.1.2.tar.gz
Platform: UNKNOWN
Classifier: Development Status :: 3 - Alpha
Classifier: Programming Language :: Python :: 3.6
